ehex.py
ehex-1.0.1.dist-info/DESCRIPTION.rst
ehex-1.0.1.dist-info/METADATA
ehex-1.0.1.dist-info/RECORD
ehex-1.0.1.dist-info/WHEEL
ehex-1.0.1.dist-info/metadata.json
ehex-1.0.1.dist-info/top_level.txt
