Metadata-Version: 2.0
Name: ehex
Version: 1.0.1
Summary: eHex module (from Traveller/Cepheus System)
Home-page: https://github.com/makhidkarun/ehex
Author: Arthur Green
Author-email: arthur.green045@gmail.com
License: MIT
Platform: UNKNOWN
